djangocms_link/__init__.py
djangocms_link/admin.py
djangocms_link/apps.py
djangocms_link/cms_plugins.py
djangocms_link/fields.py
djangocms_link/helpers.py
djangocms_link/models.py
djangocms_link/validators.py
djangocms_link/locale/af/LC_MESSAGES/django.mo
djangocms_link/locale/af/LC_MESSAGES/django.po
djangocms_link/locale/ar/LC_MESSAGES/django.mo
djangocms_link/locale/ar/LC_MESSAGES/django.po
djangocms_link/locale/be/LC_MESSAGES/django.mo
djangocms_link/locale/be/LC_MESSAGES/django.po
djangocms_link/locale/bg/LC_MESSAGES/django.mo
djangocms_link/locale/bg/LC_MESSAGES/django.po
djangocms_link/locale/bn/LC_MESSAGES/django.mo
djangocms_link/locale/bn/LC_MESSAGES/django.po
djangocms_link/locale/ca/LC_MESSAGES/django.mo
djangocms_link/locale/ca/LC_MESSAGES/django.po
djangocms_link/locale/cmn/LC_MESSAGES/django.mo
djangocms_link/locale/cmn/LC_MESSAGES/django.po
djangocms_link/locale/cs/LC_MESSAGES/django.mo
djangocms_link/locale/cs/LC_MESSAGES/django.po
djangocms_link/locale/cy/LC_MESSAGES/django.mo
djangocms_link/locale/cy/LC_MESSAGES/django.po
djangocms_link/locale/da/LC_MESSAGES/django.mo
djangocms_link/locale/da/LC_MESSAGES/django.po
djangocms_link/locale/de/LC_MESSAGES/django.mo
djangocms_link/locale/de/LC_MESSAGES/django.po
djangocms_link/locale/el/LC_MESSAGES/django.mo
djangocms_link/locale/el/LC_MESSAGES/django.po
djangocms_link/locale/en/LC_MESSAGES/django.mo
djangocms_link/locale/en/LC_MESSAGES/django.po
djangocms_link/locale/en_GB/LC_MESSAGES/django.mo
djangocms_link/locale/en_GB/LC_MESSAGES/django.po
djangocms_link/locale/en_US/LC_MESSAGES/django.mo
djangocms_link/locale/en_US/LC_MESSAGES/django.po
djangocms_link/locale/eo/LC_MESSAGES/django.mo
djangocms_link/locale/eo/LC_MESSAGES/django.po
djangocms_link/locale/es/LC_MESSAGES/django.mo
djangocms_link/locale/es/LC_MESSAGES/django.po
djangocms_link/locale/et/LC_MESSAGES/django.mo
djangocms_link/locale/et/LC_MESSAGES/django.po
djangocms_link/locale/eu/LC_MESSAGES/django.mo
djangocms_link-5.1.0.dist-info/licenses/LICENSE
djangocms_link-5.1.0.dist-info/METADATA
djangocms_link-5.1.0.dist-info/WHEEL
djangocms_link-5.1.0.dist-info/top_level.txt
djangocms_link-5.1.0.dist-info/RECORD
